juice_plasma_torus/__init__.py
juice_plasma_torus/juice_moon_plasma_sc2earth_crossing_torus_cmd.py
juice_plasma_torus/juice_moon_plasma_sc_within_torus_cmd.py
juice_plasma_torus/commons/__init__.py
juice_plasma_torus/commons/my_log.py
juice_plasma_torus/commons/mysql_connector.py
juice_plasma_torus/commons/mysql_import_dump_file.py
juice_plasma_torus/commons/numpy_utils.py
juice_plasma_torus/commons/segment_handler.py
juice_plasma_torus/plasma_torus_model/__init__.py
juice_plasma_torus/plasma_torus_model/gf_distance.py
juice_plasma_torus/plasma_torus_model/gs_elevation.py
juice_plasma_torus/plasma_torus_model/gs_occult.py
juice_plasma_torus/plasma_torus_model/moon_within_plasma_torus.py
juice_plasma_torus/plasma_torus_model/mysql_connector_plasma_torus.py
juice_plasma_torus/plasma_torus_model/plasma_torus.py
juice_plasma_torus/plasma_torus_model/sc_ray_crossing_plasma_torus.py
scripts/__init__.py
scripts/torus_pre_processing/__init__.py
scripts/torus_pre_processing/create_elipse_section.py
scripts/torus_pre_processing/torus_analysis.py
scripts/torus_pre_processing/torus_generator.py
test/__init__.py
test/query_table.py
test/plasma_torus/__init__.py
test/plasma_torus/sample_code.py
test/plasma_torus/test_dskvv_sample.py
test/plasma_torus/test_io_torus.py
juice_moon_plasma_torus-0.1.2.dist-info/METADATA
juice_moon_plasma_torus-0.1.2.dist-info/WHEEL
juice_moon_plasma_torus-0.1.2.dist-info/entry_points.txt
juice_moon_plasma_torus-0.1.2.dist-info/top_level.txt
juice_moon_plasma_torus-0.1.2.dist-info/RECORD
