Metadata-Version: 2.1
Name: juice-moon-plasma-torus
Version: 0.1.2
Summary: Python package to calculate Jupiter Moon Plasma Torus intercept by a ray spacecraft-to-body
Home-page: https://juigitlab.esac.esa.int/core-system/uplink/juice_moon_plasma_torus
Author: JUICE SOC team
Author-email: juice_soc@cosmos.esa.int
Keywords: esa,Juice,planetary,space,metrics,trajectory,assessment,crema,plasma,torus
Classifier: Development Status :: 3 - Alpha
Classifier: Intended Audience :: Science/Research
Classifier: Topic :: Scientific/Engineering :: Astronomy
Classifier: Programming Language :: Python :: 3.7
Requires-Dist: tabulate
Requires-Dist: mysql-connector-python>=8.0.32
Requires-Dist: esac-juice-pyutils>=0.2.9
